gimitest/__init__.py
gimitest/env_decorator.py
gimitest/glogger.py
gimitest/gtest.py
gimitest/gtest_decorator.py
gimitest/inspecting/__init__.py
gimitest/inspecting/inspect.py
gimitest/testing/__init__.py
gimitest/testing/random_search_based_state_independent_testing.py
gimitest-1.0.dist-info/licenses/LICENSE
gimitest-1.0.dist-info/METADATA
gimitest-1.0.dist-info/WHEEL
gimitest-1.0.dist-info/top_level.txt
gimitest-1.0.dist-info/RECORD
