Metadata-Version: 2.4
Name: gimitest
Version: 1.0
Summary: A flexible framework for evaluating reinforcement learning agents in Farama Gymnasium and PettingZoo environments.
Author-email: Gross Dennis <dennis@simula.no>, Mazouni Quentin <quentin@simula.no>, Spieker Helge <helge@simula.no>
License: MIT
Project-URL: Homepage, https://github.com/DennisGross/gimitest
Classifier: Programming Language :: Python :: 3
Classifier: Programming Language :: Python :: 3.10
Requires-Python: >=3.10
License-File: LICENSE
Requires-Dist: gymnasium==0.29.1
Requires-Dist: numpy<2.0
Requires-Dist: matplotlib
Requires-Dist: cloudpickle
Requires-Dist: contourpy
Requires-Dist: cycler
Requires-Dist: Farama-Notifications
Requires-Dist: fonttools
Requires-Dist: kiwisolver
Requires-Dist: packaging
Requires-Dist: pandas
Requires-Dist: Pillow
Requires-Dist: pyparsing
Requires-Dist: python-dateutil
Requires-Dist: pytz
Requires-Dist: scipy
Requires-Dist: seaborn
Requires-Dist: six
Requires-Dist: typing_extensions
Requires-Dist: tzdata
Provides-Extra: dev
Requires-Dist: swig; extra == "dev"
Requires-Dist: gymnasium[box2d]; extra == "dev"
Requires-Dist: MinAtar; extra == "dev"
Dynamic: license-file
